[{"value": 93881.0, "datetime": "2024-05-24T02:00:00.000+02:00", "datetime_utc": "2024-05-24T00:00:00Z", "tz_time": "2024-05-24T00:00:00.000Z", "geo_id": 8741, "geo_name": "Pen\u00ednsula"}, {"value": 88327.0, "datetime": "2024-05-24T03:00:00.000+02:00", "datetime_utc": "2024-05-24T01:00:00Z", "tz_time": "2024-05-24T01:00:00.000Z", "geo_id": 8741, "geo_name": "Pen\u00ednsula"}, {"value": 81655.0, "datetime": "2024-05-24T04:00:00.000+02:00", "datetime_utc": "2024-05-24T02:00:00Z", "tz_time": "2024-05-24T02:00:00.000Z", "geo_id": 8741, "geo_name": "Pen\u00ednsula"}, {"value": 74555.0, "datetime": "2024-05-24T05:00:00.000+02:00", "datetime_utc": "2024-05-24T03:00:00Z", "tz_time": "2024-05-24T03:00:00.000Z", "geo_id": 8741, "geo_name": "Pen\u00ednsula"}, {"value": 67620.0, "datetime": "2024-05-24T06:00:00.000+02:00", "datetime_utc": "2024-05-24T04:00:00Z", "tz_time": "2024-05-24T04:00:00.000Z", "geo_id": 8741, "geo_name": "Pen\u00ednsula"}, {"value": 59936.0, "datetime": "2024-05-24T07:00:00.000+02:00", "datetime_utc": "2024-05-24T05:00:00Z", "tz_time": "2024-05-24T05:00:00.000Z", "geo_id": 8741, "geo_name": "Pen\u00ednsula"}, {"value": 44793.0, "datetime": "2024-05-24T08:00:00.000+02:00", "datetime_utc": "2024-05-24T06:00:00Z", "tz_time": "2024-05-24T06:00:00.000Z", "geo_id": 8741, "geo_name": "Pen\u00ednsula"}, {"value": 31925.0, "datetime": "2024-05-24T09:00:00.000+02:00", "datetime_utc": "2024-05-24T07:00:00Z", "tz_time": "2024-05-24T07:00:00.000Z", "geo_id": 8741, "geo_name": "Pen\u00ednsula"}, {"value": 21699.0, "datetime": "2024-05-24T10:00:00.000+02:00", "datetime_utc": "2024-05-24T08:00:00Z", "tz_time": "2024-05-24T08:00:00.000Z", "geo_id": 8741, "geo_name": "Pen\u00ednsula"}, {"value": 16731.0, "datetime": "2024-05-24T11:00:00.000+02:00", "datetime_utc": "2024-05-24T09:00:00Z", "tz_time": "2024-05-24T09:00:00.000Z", "geo_id": 8741, "geo_name": "Pen\u00ednsula"}, {"value": 14513.0, "datetime": "2024-05-24T12:00:00.000+02:00", "datetime_utc": "2024-05-24T10:00:00Z", "tz_time": "2024-05-24T10:00:00.000Z", "geo_id": 8741, "geo_name": "Pen\u00ednsula"}, {"value": 15892.0, "datetime": "2024-05-24T13:00:00.000+02:00", "datetime_utc": "2024-05-24T11:00:00Z", "tz_time": "2024-05-24T11:00:00.000Z", "geo_id": 8741, "geo_name": "Pen\u00ednsula"}, {"value": 17290.0, "datetime": "2024-05-24T14:00:00.000+02:00", "datetime_utc": "2024-05-24T12:00:00Z", "tz_time": "2024-05-24T12:00:00.000Z", "geo_id": 8741, "geo_name": "Pen\u00ednsula"}, {"value": 19059.0, "datetime": "2024-05-24T15:00:00.000+02:00", "datetime_utc": "2024-05-24T13:00:00Z", "tz_time": "2024-05-24T13:00:00.000Z", "geo_id": 8741, "geo_name": "Pen\u00ednsula"}, {"value": 21574.0, "datetime": "2024-05-24T16:00:00.000+02:00", "datetime_utc": "2024-05-24T14:00:00Z", "tz_time": "2024-05-24T14:00:00.000Z", "geo_id": 8741, "geo_name": "Pen\u00ednsula"}, {"value": 24509.0, "datetime": "2024-05-24T17:00:00.000+02:00", "datetime_utc": "2024-05-24T15:00:00Z", "tz_time": "2024-05-24T15:00:00.000Z", "geo_id": 8741, "geo_name": "Pen\u00ednsula"}, {"value": 27354.0, "datetime": "2024-05-24T18:00:00.000+02:00", "datetime_utc": "2024-05-24T16:00:00Z", "tz_time": "2024-05-24T16:00:00.000Z", "geo_id": 8741, "geo_name": "Pen\u00ednsula"}, {"value": 28207.0, "datetime": "2024-05-24T19:00:00.000+02:00", "datetime_utc": "2024-05-24T17:00:00Z", "tz_time": "2024-05-24T17:00:00.000Z", "geo_id": 8741, "geo_name": "Pen\u00ednsula"}, {"value": 28719.0, "datetime": "2024-05-24T20:00:00.000+02:00", "datetime_utc": "2024-05-24T18:00:00Z", "tz_time": "2024-05-24T18:00:00.000Z", "geo_id": 8741, "geo_name": "Pen\u00ednsula"}, {"value": 27762.0, "datetime": "2024-05-24T21:00:00.000+02:00", "datetime_utc": "2024-05-24T19:00:00Z", "tz_time": "2024-05-24T19:00:00.000Z", "geo_id": 8741, "geo_name": "Pen\u00ednsula"}, {"value": 27178.0, "datetime": "2024-05-24T22:00:00.000+02:00", "datetime_utc": "2024-05-24T20:00:00Z", "tz_time": "2024-05-24T20:00:00.000Z", "geo_id": 8741, "geo_name": "Pen\u00ednsula"}, {"value": 25047.0, "datetime": "2024-05-24T23:00:00.000+02:00", "datetime_utc": "2024-05-24T21:00:00Z", "tz_time": "2024-05-24T21:00:00.000Z", "geo_id": 8741, "geo_name": "Pen\u00ednsula"}, {"value": 22211.0, "datetime": "2024-05-25T00:00:00.000+02:00", "datetime_utc": "2024-05-24T22:00:00Z", "tz_time": "2024-05-24T22:00:00.000Z", "geo_id": 8741, "geo_name": "Pen\u00ednsula"}, {"value": 1865.0, "datetime": "2024-05-25T01:00:00.000+02:00", "datetime_utc": "2024-05-24T23:00:00Z", "tz_time": "2024-05-24T23:00:00.000Z", "geo_id": 8741, "geo_name": "Pen\u00ednsula"}]