[{"value": 86184.0, "datetime": "2024-07-04T02:00:00.000+02:00", "datetime_utc": "2024-07-04T00:00:00Z", "tz_time": "2024-07-04T00:00:00.000Z", "geo_id": 8741, "geo_name": "Pen\u00ednsula"}, {"value": 85268.0, "datetime": "2024-07-04T03:00:00.000+02:00", "datetime_utc": "2024-07-04T01:00:00Z", "tz_time": "2024-07-04T01:00:00.000Z", "geo_id": 8741, "geo_name": "Pen\u00ednsula"}, {"value": 83036.0, "datetime": "2024-07-04T04:00:00.000+02:00", "datetime_utc": "2024-07-04T02:00:00Z", "tz_time": "2024-07-04T02:00:00.000Z", "geo_id": 8741, "geo_name": "Pen\u00ednsula"}, {"value": 79347.0, "datetime": "2024-07-04T05:00:00.000+02:00", "datetime_utc": "2024-07-04T03:00:00Z", "tz_time": "2024-07-04T03:00:00.000Z", "geo_id": 8741, "geo_name": "Pen\u00ednsula"}, {"value": 79032.0, "datetime": "2024-07-04T06:00:00.000+02:00", "datetime_utc": "2024-07-04T04:00:00Z", "tz_time": "2024-07-04T04:00:00.000Z", "geo_id": 8741, "geo_name": "Pen\u00ednsula"}, {"value": 74464.0, "datetime": "2024-07-04T07:00:00.000+02:00", "datetime_utc": "2024-07-04T05:00:00Z", "tz_time": "2024-07-04T05:00:00.000Z", "geo_id": 8741, "geo_name": "Pen\u00ednsula"}, {"value": 65289.0, "datetime": "2024-07-04T08:00:00.000+02:00", "datetime_utc": "2024-07-04T06:00:00Z", "tz_time": "2024-07-04T06:00:00.000Z", "geo_id": 8741, "geo_name": "Pen\u00ednsula"}, {"value": 57497.0, "datetime": "2024-07-04T09:00:00.000+02:00", "datetime_utc": "2024-07-04T07:00:00Z", "tz_time": "2024-07-04T07:00:00.000Z", "geo_id": 8741, "geo_name": "Pen\u00ednsula"}, {"value": 50823.0, "datetime": "2024-07-04T10:00:00.000+02:00", "datetime_utc": "2024-07-04T08:00:00Z", "tz_time": "2024-07-04T08:00:00.000Z", "geo_id": 8741, "geo_name": "Pen\u00ednsula"}, {"value": 48930.0, "datetime": "2024-07-04T11:00:00.000+02:00", "datetime_utc": "2024-07-04T09:00:00Z", "tz_time": "2024-07-04T09:00:00.000Z", "geo_id": 8741, "geo_name": "Pen\u00ednsula"}, {"value": 50307.0, "datetime": "2024-07-04T12:00:00.000+02:00", "datetime_utc": "2024-07-04T10:00:00Z", "tz_time": "2024-07-04T10:00:00.000Z", "geo_id": 8741, "geo_name": "Pen\u00ednsula"}, {"value": 49700.0, "datetime": "2024-07-04T13:00:00.000+02:00", "datetime_utc": "2024-07-04T11:00:00Z", "tz_time": "2024-07-04T11:00:00.000Z", "geo_id": 8741, "geo_name": "Pen\u00ednsula"}, {"value": 49786.0, "datetime": "2024-07-04T14:00:00.000+02:00", "datetime_utc": "2024-07-04T12:00:00Z", "tz_time": "2024-07-04T12:00:00.000Z", "geo_id": 8741, "geo_name": "Pen\u00ednsula"}, {"value": 50051.0, "datetime": "2024-07-04T15:00:00.000+02:00", "datetime_utc": "2024-07-04T13:00:00Z", "tz_time": "2024-07-04T13:00:00.000Z", "geo_id": 8741, "geo_name": "Pen\u00ednsula"}, {"value": 51938.0, "datetime": "2024-07-04T16:00:00.000+02:00", "datetime_utc": "2024-07-04T14:00:00Z", "tz_time": "2024-07-04T14:00:00.000Z", "geo_id": 8741, "geo_name": "Pen\u00ednsula"}, {"value": 56280.0, "datetime": "2024-07-04T17:00:00.000+02:00", "datetime_utc": "2024-07-04T15:00:00Z", "tz_time": "2024-07-04T15:00:00.000Z", "geo_id": 8741, "geo_name": "Pen\u00ednsula"}, {"value": 62461.0, "datetime": "2024-07-04T18:00:00.000+02:00", "datetime_utc": "2024-07-04T16:00:00Z", "tz_time": "2024-07-04T16:00:00.000Z", "geo_id": 8741, "geo_name": "Pen\u00ednsula"}, {"value": 66896.0, "datetime": "2024-07-04T19:00:00.000+02:00", "datetime_utc": "2024-07-04T17:00:00Z", "tz_time": "2024-07-04T17:00:00.000Z", "geo_id": 8741, "geo_name": "Pen\u00ednsula"}, {"value": 71612.0, "datetime": "2024-07-04T20:00:00.000+02:00", "datetime_utc": "2024-07-04T18:00:00Z", "tz_time": "2024-07-04T18:00:00.000Z", "geo_id": 8741, "geo_name": "Pen\u00ednsula"}, {"value": 83414.0, "datetime": "2024-07-04T21:00:00.000+02:00", "datetime_utc": "2024-07-04T19:00:00Z", "tz_time": "2024-07-04T19:00:00.000Z", "geo_id": 8741, "geo_name": "Pen\u00ednsula"}, {"value": 100475.0, "datetime": "2024-07-04T22:00:00.000+02:00", "datetime_utc": "2024-07-04T20:00:00Z", "tz_time": "2024-07-04T20:00:00.000Z", "geo_id": 8741, "geo_name": "Pen\u00ednsula"}, {"value": 106048.0, "datetime": "2024-07-04T23:00:00.000+02:00", "datetime_utc": "2024-07-04T21:00:00Z", "tz_time": "2024-07-04T21:00:00.000Z", "geo_id": 8741, "geo_name": "Pen\u00ednsula"}, {"value": 106158.0, "datetime": "2024-07-05T00:00:00.000+02:00", "datetime_utc": "2024-07-04T22:00:00Z", "tz_time": "2024-07-04T22:00:00.000Z", "geo_id": 8741, "geo_name": "Pen\u00ednsula"}, {"value": 8834.0, "datetime": "2024-07-05T01:00:00.000+02:00", "datetime_utc": "2024-07-04T23:00:00Z", "tz_time": "2024-07-04T23:00:00.000Z", "geo_id": 8741, "geo_name": "Pen\u00ednsula"}]