[{"value": 3706.9, "datetime": "2024-05-05T02:00:00.000+02:00", "datetime_utc": "2024-05-05T00:00:00Z", "tz_time": "2024-05-05T00:00:00.000Z", "geo_id": 8741, "geo_name": "Pen\u00ednsula"}, {"value": 3683.5, "datetime": "2024-05-05T03:00:00.000+02:00", "datetime_utc": "2024-05-05T01:00:00Z", "tz_time": "2024-05-05T01:00:00.000Z", "geo_id": 8741, "geo_name": "Pen\u00ednsula"}, {"value": 3518.1, "datetime": "2024-05-05T04:00:00.000+02:00", "datetime_utc": "2024-05-05T02:00:00Z", "tz_time": "2024-05-05T02:00:00.000Z", "geo_id": 8741, "geo_name": "Pen\u00ednsula"}, {"value": 3489.2, "datetime": "2024-05-05T05:00:00.000+02:00", "datetime_utc": "2024-05-05T03:00:00Z", "tz_time": "2024-05-05T03:00:00.000Z", "geo_id": 8741, "geo_name": "Pen\u00ednsula"}, {"value": 3524.6, "datetime": "2024-05-05T06:00:00.000+02:00", "datetime_utc": "2024-05-05T04:00:00Z", "tz_time": "2024-05-05T04:00:00.000Z", "geo_id": 8741, "geo_name": "Pen\u00ednsula"}, {"value": 3389.3, "datetime": "2024-05-05T07:00:00.000+02:00", "datetime_utc": "2024-05-05T05:00:00Z", "tz_time": "2024-05-05T05:00:00.000Z", "geo_id": 8741, "geo_name": "Pen\u00ednsula"}, {"value": 2988.1, "datetime": "2024-05-05T08:00:00.000+02:00", "datetime_utc": "2024-05-05T06:00:00Z", "tz_time": "2024-05-05T06:00:00.000Z", "geo_id": 8741, "geo_name": "Pen\u00ednsula"}, {"value": 2468.8, "datetime": "2024-05-05T09:00:00.000+02:00", "datetime_utc": "2024-05-05T07:00:00Z", "tz_time": "2024-05-05T07:00:00.000Z", "geo_id": 8741, "geo_name": "Pen\u00ednsula"}, {"value": 2228.6, "datetime": "2024-05-05T10:00:00.000+02:00", "datetime_utc": "2024-05-05T08:00:00Z", "tz_time": "2024-05-05T08:00:00.000Z", "geo_id": 8741, "geo_name": "Pen\u00ednsula"}, {"value": 2169.1, "datetime": "2024-05-05T11:00:00.000+02:00", "datetime_utc": "2024-05-05T09:00:00Z", "tz_time": "2024-05-05T09:00:00.000Z", "geo_id": 8741, "geo_name": "Pen\u00ednsula"}, {"value": 2101.2, "datetime": "2024-05-05T12:00:00.000+02:00", "datetime_utc": "2024-05-05T10:00:00Z", "tz_time": "2024-05-05T10:00:00.000Z", "geo_id": 8741, "geo_name": "Pen\u00ednsula"}, {"value": 2082.6, "datetime": "2024-05-05T13:00:00.000+02:00", "datetime_utc": "2024-05-05T11:00:00Z", "tz_time": "2024-05-05T11:00:00.000Z", "geo_id": 8741, "geo_name": "Pen\u00ednsula"}, {"value": 2048.6, "datetime": "2024-05-05T14:00:00.000+02:00", "datetime_utc": "2024-05-05T12:00:00Z", "tz_time": "2024-05-05T12:00:00.000Z", "geo_id": 8741, "geo_name": "Pen\u00ednsula"}, {"value": 2027.9, "datetime": "2024-05-05T15:00:00.000+02:00", "datetime_utc": "2024-05-05T13:00:00Z", "tz_time": "2024-05-05T13:00:00.000Z", "geo_id": 8741, "geo_name": "Pen\u00ednsula"}, {"value": 2024.2, "datetime": "2024-05-05T16:00:00.000+02:00", "datetime_utc": "2024-05-05T14:00:00Z", "tz_time": "2024-05-05T14:00:00.000Z", "geo_id": 8741, "geo_name": "Pen\u00ednsula"}, {"value": 2024.0, "datetime": "2024-05-05T17:00:00.000+02:00", "datetime_utc": "2024-05-05T15:00:00Z", "tz_time": "2024-05-05T15:00:00.000Z", "geo_id": 8741, "geo_name": "Pen\u00ednsula"}, {"value": 2204.2, "datetime": "2024-05-05T18:00:00.000+02:00", "datetime_utc": "2024-05-05T16:00:00Z", "tz_time": "2024-05-05T16:00:00.000Z", "geo_id": 8741, "geo_name": "Pen\u00ednsula"}, {"value": 2669.6, "datetime": "2024-05-05T19:00:00.000+02:00", "datetime_utc": "2024-05-05T17:00:00Z", "tz_time": "2024-05-05T17:00:00.000Z", "geo_id": 8741, "geo_name": "Pen\u00ednsula"}, {"value": 4604.4, "datetime": "2024-05-05T20:00:00.000+02:00", "datetime_utc": "2024-05-05T18:00:00Z", "tz_time": "2024-05-05T18:00:00.000Z", "geo_id": 8741, "geo_name": "Pen\u00ednsula"}, {"value": 5205.6, "datetime": "2024-05-05T21:00:00.000+02:00", "datetime_utc": "2024-05-05T19:00:00Z", "tz_time": "2024-05-05T19:00:00.000Z", "geo_id": 8741, "geo_name": "Pen\u00ednsula"}, {"value": 5191.8, "datetime": "2024-05-05T22:00:00.000+02:00", "datetime_utc": "2024-05-05T20:00:00Z", "tz_time": "2024-05-05T20:00:00.000Z", "geo_id": 8741, "geo_name": "Pen\u00ednsula"}, {"value": 5111.8, "datetime": "2024-05-05T23:00:00.000+02:00", "datetime_utc": "2024-05-05T21:00:00Z", "tz_time": "2024-05-05T21:00:00.000Z", "geo_id": 8741, "geo_name": "Pen\u00ednsula"}, {"value": 3600.9, "datetime": "2024-05-06T00:00:00.000+02:00", "datetime_utc": "2024-05-05T22:00:00Z", "tz_time": "2024-05-05T22:00:00.000Z", "geo_id": 8741, "geo_name": "Pen\u00ednsula"}, {"value": 3073.8, "datetime": "2024-05-06T01:00:00.000+02:00", "datetime_utc": "2024-05-05T23:00:00Z", "tz_time": "2024-05-05T23:00:00.000Z", "geo_id": 8741, "geo_name": "Pen\u00ednsula"}]