[{"value": 3590.6, "datetime": "2024-05-27T02:00:00.000+02:00", "datetime_utc": "2024-05-27T00:00:00Z", "tz_time": "2024-05-27T00:00:00.000Z", "geo_id": 8741, "geo_name": "Pen\u00ednsula"}, {"value": 3562.8, "datetime": "2024-05-27T03:00:00.000+02:00", "datetime_utc": "2024-05-27T01:00:00Z", "tz_time": "2024-05-27T01:00:00.000Z", "geo_id": 8741, "geo_name": "Pen\u00ednsula"}, {"value": 3518.2, "datetime": "2024-05-27T04:00:00.000+02:00", "datetime_utc": "2024-05-27T02:00:00Z", "tz_time": "2024-05-27T02:00:00.000Z", "geo_id": 8741, "geo_name": "Pen\u00ednsula"}, {"value": 3611.9, "datetime": "2024-05-27T05:00:00.000+02:00", "datetime_utc": "2024-05-27T03:00:00Z", "tz_time": "2024-05-27T03:00:00.000Z", "geo_id": 8741, "geo_name": "Pen\u00ednsula"}, {"value": 3861.8, "datetime": "2024-05-27T06:00:00.000+02:00", "datetime_utc": "2024-05-27T04:00:00Z", "tz_time": "2024-05-27T04:00:00.000Z", "geo_id": 8741, "geo_name": "Pen\u00ednsula"}, {"value": 4510.1, "datetime": "2024-05-27T07:00:00.000+02:00", "datetime_utc": "2024-05-27T05:00:00Z", "tz_time": "2024-05-27T05:00:00.000Z", "geo_id": 8741, "geo_name": "Pen\u00ednsula"}, {"value": 4288.8, "datetime": "2024-05-27T08:00:00.000+02:00", "datetime_utc": "2024-05-27T06:00:00Z", "tz_time": "2024-05-27T06:00:00.000Z", "geo_id": 8741, "geo_name": "Pen\u00ednsula"}, {"value": 3026.8, "datetime": "2024-05-27T09:00:00.000+02:00", "datetime_utc": "2024-05-27T07:00:00Z", "tz_time": "2024-05-27T07:00:00.000Z", "geo_id": 8741, "geo_name": "Pen\u00ednsula"}, {"value": 2515.0, "datetime": "2024-05-27T10:00:00.000+02:00", "datetime_utc": "2024-05-27T08:00:00Z", "tz_time": "2024-05-27T08:00:00.000Z", "geo_id": 8741, "geo_name": "Pen\u00ednsula"}, {"value": 2377.4, "datetime": "2024-05-27T11:00:00.000+02:00", "datetime_utc": "2024-05-27T09:00:00Z", "tz_time": "2024-05-27T09:00:00.000Z", "geo_id": 8741, "geo_name": "Pen\u00ednsula"}, {"value": 2090.0, "datetime": "2024-05-27T12:00:00.000+02:00", "datetime_utc": "2024-05-27T10:00:00Z", "tz_time": "2024-05-27T10:00:00.000Z", "geo_id": 8741, "geo_name": "Pen\u00ednsula"}, {"value": 1754.9, "datetime": "2024-05-27T13:00:00.000+02:00", "datetime_utc": "2024-05-27T11:00:00Z", "tz_time": "2024-05-27T11:00:00.000Z", "geo_id": 8741, "geo_name": "Pen\u00ednsula"}, {"value": 1776.0, "datetime": "2024-05-27T14:00:00.000+02:00", "datetime_utc": "2024-05-27T12:00:00Z", "tz_time": "2024-05-27T12:00:00.000Z", "geo_id": 8741, "geo_name": "Pen\u00ednsula"}, {"value": 1797.6, "datetime": "2024-05-27T15:00:00.000+02:00", "datetime_utc": "2024-05-27T13:00:00Z", "tz_time": "2024-05-27T13:00:00.000Z", "geo_id": 8741, "geo_name": "Pen\u00ednsula"}, {"value": 1794.4, "datetime": "2024-05-27T16:00:00.000+02:00", "datetime_utc": "2024-05-27T14:00:00Z", "tz_time": "2024-05-27T14:00:00.000Z", "geo_id": 8741, "geo_name": "Pen\u00ednsula"}, {"value": 1807.8, "datetime": "2024-05-27T17:00:00.000+02:00", "datetime_utc": "2024-05-27T15:00:00Z", "tz_time": "2024-05-27T15:00:00.000Z", "geo_id": 8741, "geo_name": "Pen\u00ednsula"}, {"value": 2531.1, "datetime": "2024-05-27T18:00:00.000+02:00", "datetime_utc": "2024-05-27T16:00:00Z", "tz_time": "2024-05-27T16:00:00.000Z", "geo_id": 8741, "geo_name": "Pen\u00ednsula"}, {"value": 2690.5, "datetime": "2024-05-27T19:00:00.000+02:00", "datetime_utc": "2024-05-27T17:00:00Z", "tz_time": "2024-05-27T17:00:00.000Z", "geo_id": 8741, "geo_name": "Pen\u00ednsula"}, {"value": 3988.3, "datetime": "2024-05-27T20:00:00.000+02:00", "datetime_utc": "2024-05-27T18:00:00Z", "tz_time": "2024-05-27T18:00:00.000Z", "geo_id": 8741, "geo_name": "Pen\u00ednsula"}, {"value": 4842.1, "datetime": "2024-05-27T21:00:00.000+02:00", "datetime_utc": "2024-05-27T19:00:00Z", "tz_time": "2024-05-27T19:00:00.000Z", "geo_id": 8741, "geo_name": "Pen\u00ednsula"}, {"value": 4851.2, "datetime": "2024-05-27T22:00:00.000+02:00", "datetime_utc": "2024-05-27T20:00:00Z", "tz_time": "2024-05-27T20:00:00.000Z", "geo_id": 8741, "geo_name": "Pen\u00ednsula"}, {"value": 4336.5, "datetime": "2024-05-27T23:00:00.000+02:00", "datetime_utc": "2024-05-27T21:00:00Z", "tz_time": "2024-05-27T21:00:00.000Z", "geo_id": 8741, "geo_name": "Pen\u00ednsula"}, {"value": 4854.2, "datetime": "2024-05-28T00:00:00.000+02:00", "datetime_utc": "2024-05-27T22:00:00Z", "tz_time": "2024-05-27T22:00:00.000Z", "geo_id": 8741, "geo_name": "Pen\u00ednsula"}, {"value": 4047.5, "datetime": "2024-05-28T01:00:00.000+02:00", "datetime_utc": "2024-05-27T23:00:00Z", "tz_time": "2024-05-27T23:00:00.000Z", "geo_id": 8741, "geo_name": "Pen\u00ednsula"}]