[{"value": 3265.3, "datetime": "2024-04-24T02:00:00.000+02:00", "datetime_utc": "2024-04-24T00:00:00Z", "tz_time": "2024-04-24T00:00:00.000Z", "geo_id": 8741, "geo_name": "Pen\u00ednsula"}, {"value": 3250.2, "datetime": "2024-04-24T03:00:00.000+02:00", "datetime_utc": "2024-04-24T01:00:00Z", "tz_time": "2024-04-24T01:00:00.000Z", "geo_id": 8741, "geo_name": "Pen\u00ednsula"}, {"value": 3345.9, "datetime": "2024-04-24T04:00:00.000+02:00", "datetime_utc": "2024-04-24T02:00:00Z", "tz_time": "2024-04-24T02:00:00.000Z", "geo_id": 8741, "geo_name": "Pen\u00ednsula"}, {"value": 3379.7, "datetime": "2024-04-24T05:00:00.000+02:00", "datetime_utc": "2024-04-24T03:00:00Z", "tz_time": "2024-04-24T03:00:00.000Z", "geo_id": 8741, "geo_name": "Pen\u00ednsula"}, {"value": 4537.2, "datetime": "2024-04-24T06:00:00.000+02:00", "datetime_utc": "2024-04-24T04:00:00Z", "tz_time": "2024-04-24T04:00:00.000Z", "geo_id": 8741, "geo_name": "Pen\u00ednsula"}, {"value": 6767.6, "datetime": "2024-04-24T07:00:00.000+02:00", "datetime_utc": "2024-04-24T05:00:00Z", "tz_time": "2024-04-24T05:00:00.000Z", "geo_id": 8741, "geo_name": "Pen\u00ednsula"}, {"value": 5678.2, "datetime": "2024-04-24T08:00:00.000+02:00", "datetime_utc": "2024-04-24T06:00:00Z", "tz_time": "2024-04-24T06:00:00.000Z", "geo_id": 8741, "geo_name": "Pen\u00ednsula"}, {"value": 2820.9, "datetime": "2024-04-24T09:00:00.000+02:00", "datetime_utc": "2024-04-24T07:00:00Z", "tz_time": "2024-04-24T07:00:00.000Z", "geo_id": 8741, "geo_name": "Pen\u00ednsula"}, {"value": 2268.0, "datetime": "2024-04-24T10:00:00.000+02:00", "datetime_utc": "2024-04-24T08:00:00Z", "tz_time": "2024-04-24T08:00:00.000Z", "geo_id": 8741, "geo_name": "Pen\u00ednsula"}, {"value": 2209.9, "datetime": "2024-04-24T11:00:00.000+02:00", "datetime_utc": "2024-04-24T09:00:00Z", "tz_time": "2024-04-24T09:00:00.000Z", "geo_id": 8741, "geo_name": "Pen\u00ednsula"}, {"value": 2215.8, "datetime": "2024-04-24T12:00:00.000+02:00", "datetime_utc": "2024-04-24T10:00:00Z", "tz_time": "2024-04-24T10:00:00.000Z", "geo_id": 8741, "geo_name": "Pen\u00ednsula"}, {"value": 2161.6, "datetime": "2024-04-24T13:00:00.000+02:00", "datetime_utc": "2024-04-24T11:00:00Z", "tz_time": "2024-04-24T11:00:00.000Z", "geo_id": 8741, "geo_name": "Pen\u00ednsula"}, {"value": 2082.1, "datetime": "2024-04-24T14:00:00.000+02:00", "datetime_utc": "2024-04-24T12:00:00Z", "tz_time": "2024-04-24T12:00:00.000Z", "geo_id": 8741, "geo_name": "Pen\u00ednsula"}, {"value": 2091.0, "datetime": "2024-04-24T15:00:00.000+02:00", "datetime_utc": "2024-04-24T13:00:00Z", "tz_time": "2024-04-24T13:00:00.000Z", "geo_id": 8741, "geo_name": "Pen\u00ednsula"}, {"value": 2109.4, "datetime": "2024-04-24T16:00:00.000+02:00", "datetime_utc": "2024-04-24T14:00:00Z", "tz_time": "2024-04-24T14:00:00.000Z", "geo_id": 8741, "geo_name": "Pen\u00ednsula"}, {"value": 2117.1, "datetime": "2024-04-24T17:00:00.000+02:00", "datetime_utc": "2024-04-24T15:00:00Z", "tz_time": "2024-04-24T15:00:00.000Z", "geo_id": 8741, "geo_name": "Pen\u00ednsula"}, {"value": 2226.4, "datetime": "2024-04-24T18:00:00.000+02:00", "datetime_utc": "2024-04-24T16:00:00Z", "tz_time": "2024-04-24T16:00:00.000Z", "geo_id": 8741, "geo_name": "Pen\u00ednsula"}, {"value": 3862.2, "datetime": "2024-04-24T19:00:00.000+02:00", "datetime_utc": "2024-04-24T17:00:00Z", "tz_time": "2024-04-24T17:00:00.000Z", "geo_id": 8741, "geo_name": "Pen\u00ednsula"}, {"value": 7513.9, "datetime": "2024-04-24T20:00:00.000+02:00", "datetime_utc": "2024-04-24T18:00:00Z", "tz_time": "2024-04-24T18:00:00.000Z", "geo_id": 8741, "geo_name": "Pen\u00ednsula"}, {"value": 8161.1, "datetime": "2024-04-24T21:00:00.000+02:00", "datetime_utc": "2024-04-24T19:00:00Z", "tz_time": "2024-04-24T19:00:00.000Z", "geo_id": 8741, "geo_name": "Pen\u00ednsula"}, {"value": 7625.3, "datetime": "2024-04-24T22:00:00.000+02:00", "datetime_utc": "2024-04-24T20:00:00Z", "tz_time": "2024-04-24T20:00:00.000Z", "geo_id": 8741, "geo_name": "Pen\u00ednsula"}, {"value": 7436.3, "datetime": "2024-04-24T23:00:00.000+02:00", "datetime_utc": "2024-04-24T21:00:00Z", "tz_time": "2024-04-24T21:00:00.000Z", "geo_id": 8741, "geo_name": "Pen\u00ednsula"}, {"value": 7499.3, "datetime": "2024-04-25T00:00:00.000+02:00", "datetime_utc": "2024-04-24T22:00:00Z", "tz_time": "2024-04-24T22:00:00.000Z", "geo_id": 8741, "geo_name": "Pen\u00ednsula"}, {"value": 7314.9, "datetime": "2024-04-25T01:00:00.000+02:00", "datetime_utc": "2024-04-24T23:00:00Z", "tz_time": "2024-04-24T23:00:00.000Z", "geo_id": 8741, "geo_name": "Pen\u00ednsula"}]